{
  "products": {
    "URUN-214462-65183": {
      "offcuts": [],
      "name": "Saray halı",
      "price": 2450,
      "stock": 50,
      "size": 6,
      "unit": "M²",
      "extraLabel": "Skt",
      "extraValue": "20.13.2026"
    },
    "URUN-214462-81352": {
      "offcuts": [],
      "name": "Enes zeytin gold",
      "price": 4750,
      "stock": 25,
      "size": 18,
      "unit": "KG",
      "extraLabel": "Skt",
      "extraValue": "11.08.2027"
    },
    "URUN-536063-65751": {
      "offcuts": [],
      "name": "Kent rang blue",
      "price": 100,
      "stock": 45,
      "size": 0,
      "unit": "M²",
      "extraLabel": "",
      "extraValue": ""
    },
    "URUN-536063-63553": {
      "offcuts": [],
      "name": "Zeytin",
      "price": 4500,
      "stock": 0,
      "size": 18,
      "unit": "KG",
      "extraLabel": "Skt",
      "extraValue": "446.66.77"
    }
  },
  "dailyStats": {
    "date": "10.02.2026",
    "ciro": 500,
    "log": [
      {
        "name": "Kent rang blue",
        "qty": 5,
        "total": 500,
        "staff": "Frh"
      }
    ]
  }
}